precise/PRECISE.py
precise/__init__.py
precise/interpolation.py
precise/kernel_computer.py
precise/matrix_operations.py
precise/pv_computation.py
precise_plus-1.0.2.dist-info/LICENSE
precise_plus-1.0.2.dist-info/METADATA
precise_plus-1.0.2.dist-info/WHEEL
precise_plus-1.0.2.dist-info/top_level.txt
precise_plus-1.0.2.dist-info/RECORD
