Metadata-Version: 2.1
Name: precise-plus
Version: 1.0.2
Summary: PRECISE+
Home-page: https://github.com/NKI-CCB/PRECISE_plus
Author: Soufiane Mourragui <soufiane.mourragui@gmail.com>, 
Author-email: soufiane.mourragui@gmail.com
License: UNKNOWN
Platform: UNKNOWN
Classifier: Programming Language :: Python :: 3
Classifier: License :: OSI Approved :: MIT License
Classifier: Operating System :: OS Independent
Classifier: Topic :: Scientific/Engineering :: Bio-Informatics
Classifier: Development Status :: 1 - Planning
Requires-Python: >=3.6
Requires-Dist: numpy
Requires-Dist: scipy
Requires-Dist: pandas
Requires-Dist: matplotlib
Requires-Dist: scikit-learn
